p115tinydav/__init__.py
p115tinydav/__main__.py
p115tinydav/app.py
p115tinydav/py.typed
p115tinydav-0.0.1.dist-info/METADATA
p115tinydav-0.0.1.dist-info/WHEEL
p115tinydav-0.0.1.dist-info/entry_points.txt
p115tinydav-0.0.1.dist-info/licenses/LICENSE
p115tinydav-0.0.1.dist-info/RECORD
