Metadata-Version: 2.4
Name: p115tinydav
Version: 0.0.1
Summary: 115 tiny webdav.
License: MIT
License-File: LICENSE
Keywords: python-115,webdav
Author: ChenyangGao
Author-email: wosiwujm@gmail.com
Requires-Python: >=3.12,<4.0
Classifier: Development Status :: 5 - Production/Stable
Classifier: Intended Audience :: Developers
Classifier: License :: OSI Approved :: MIT License
Classifier: Operating System :: OS Independent
Classifier: Programming Language :: Python
Classifier: Programming Language :: Python :: 3
Classifier: Programming Language :: Python :: 3.12
Classifier: Programming Language :: Python :: 3.13
Classifier: Programming Language :: Python :: 3.14
Classifier: Programming Language :: Python :: 3 :: Only
Classifier: Topic :: Software Development
Classifier: Topic :: Software Development :: Libraries
Classifier: Topic :: Software Development :: Libraries :: Python Modules
Requires-Dist: blacksheep
Requires-Dist: blacksheep-rich-log (>=0.0.1)
Requires-Dist: cachedict (>=0.0.6)
Requires-Dist: datefmt (>=0.0.1)
Requires-Dist: errno2 (>=0.0.5)
Requires-Dist: p115client (>=0.0.7.7.1)
Requires-Dist: python-sqlitedict (>=0.0.3)
Requires-Dist: pyyaml
Requires-Dist: uvicorn
Requires-Dist: yarl
Project-URL: Homepage, https://github.com/ChenyangGao/p115client/tree/main/modules/p115tinydav
Project-URL: Repository, https://github.com/ChenyangGao/p115client/tree/main/modules/p115tinydav
